hermit/__init__.py
hermit/config.py
hermit/errors.py
hermit/plugin.py
hermit/rng.py
hermit/shamir_share.py
hermit/wallet.py
hermit/qrcode/__init__.py
hermit/qrcode/displayer.py
hermit/qrcode/format.py
hermit/qrcode/reader.py
hermit/qrcode/utils.py
hermit/shards/__init__.py
hermit/shards/interface.py
hermit/shards/shard.py
hermit/shards/shard_set.py
hermit/signer/__init__.py
hermit/signer/base.py
hermit/signer/bitcoin_signer.py
hermit/signer/echo_signer.py
hermit/ui/__init__.py
hermit/ui/base.py
hermit/ui/common.py
hermit/ui/main.py
hermit/ui/relocker.py
hermit/ui/repl.py
hermit/ui/shards.py
hermit/ui/state.py
hermit/ui/toolbar.py
hermit/ui/wallet.py
hermit/wordlists/__init__.py
hermit/wordlists/shard.txt
hermit/wordlists/wallet.txt
hermit-0.1.12.data/data/hermit/shard.txt
hermit-0.1.12.data/data/hermit/wallet.txt
hermit-0.1.12.data/data/pybitcointools/english.txt
hermit-0.1.12.data/scripts/hermit
pybitcointools/__init__.py
pybitcointools/bci.py
pybitcointools/blocks.py
pybitcointools/composite.py
pybitcointools/deterministic.py
pybitcointools/english.txt
pybitcointools/main.py
pybitcointools/mnemonic.py
pybitcointools/py2specials.py
pybitcointools/py3specials.py
pybitcointools/ripemd.py
pybitcointools/stealth.py
pybitcointools/transaction.py
hermit-0.1.12.dist-info/LICENSE
hermit-0.1.12.dist-info/METADATA
hermit-0.1.12.dist-info/WHEEL
hermit-0.1.12.dist-info/top_level.txt
hermit-0.1.12.dist-info/RECORD
