Metadata-Version: 2.1
Name: hermit
Version: 0.1.12
Summary: Unchained Capital Hermit
Home-page: https://github.com/unchained-captial/hermit
Author: Unchained Capital Engineering
Author-email: engineering@unchained-capital.com
License: UNKNOWN
Platform: UNKNOWN
Classifier: Programming Language :: Python :: 3
Classifier: License :: OSI Approved :: Apache Software License
Classifier: Operating System :: OS Independent
Requires-Dist: Babel (==2.7.0)
Requires-Dist: Click (==7.0)
Requires-Dist: Jinja2 (==2.10.1)
Requires-Dist: MarkupSafe (==1.1.1)
Requires-Dist: Pillow (==6.2.0)
Requires-Dist: PyYAML (==5.1.1)
Requires-Dist: Pygments (==2.4.2)
Requires-Dist: Sphinx (==1.8.5)
Requires-Dist: alabaster (==0.7.12)
Requires-Dist: asn1crypto (==0.24.0)
Requires-Dist: atomicwrites (==1.3.0)
Requires-Dist: attrs (==19.1.0)
Requires-Dist: bleach (==3.1.0)
Requires-Dist: bson (==0.5.8)
Requires-Dist: certifi (==2019.6.16)
Requires-Dist: cffi (==1.12.3)
Requires-Dist: chardet (==3.0.4)
Requires-Dist: colorama (==0.4.1)
Requires-Dist: coverage (==4.5.4)
Requires-Dist: cryptography (==2.7)
Requires-Dist: docutils (==0.15.2)
Requires-Dist: ecdsa (==0.13.3)
Requires-Dist: entrypoints (==0.3)
Requires-Dist: flake8 (==3.7.7)
Requires-Dist: idna (==2.8)
Requires-Dist: imagesize (==1.1.0)
Requires-Dist: importlib-metadata (==0.19)
Requires-Dist: imutils (==0.5.1)
Requires-Dist: mccabe (==0.6.1)
Requires-Dist: mnemonic (==0.18)
Requires-Dist: more-itertools (==7.2.0)
Requires-Dist: mypy-extensions (==0.4.1)
Requires-Dist: mypy (==0.701)
Requires-Dist: numpy (==1.17.0)
Requires-Dist: opencv-python (==3.4.3.18)
Requires-Dist: packaging (==19.1)
Requires-Dist: pbkdf2 (==1.3)
Requires-Dist: pkginfo (==1.5.0.1)
Requires-Dist: pluggy (==0.12.0)
Requires-Dist: prompt-toolkit (==2.0.7)
Requires-Dist: py (==1.8.0)
Requires-Dist: pyAesCrypt (==0.4.2)
Requires-Dist: pycodestyle (==2.5.0)
Requires-Dist: pycparser (==2.19)
Requires-Dist: pyflakes (==2.1.1)
Requires-Dist: pyparsing (==2.4.2)
Requires-Dist: pysha3 (==1.0.2)
Requires-Dist: pytest-cov (==2.6.1)
Requires-Dist: pytest (==4.4.0)
Requires-Dist: python-bitcoinlib (==0.10.1)
Requires-Dist: python-dateutil (==2.8.0)
Requires-Dist: pytz (==2019.2)
Requires-Dist: pyzbar (==0.1.7)
Requires-Dist: qrcode (==6.0)
Requires-Dist: readme-renderer (==24.0)
Requires-Dist: requests-toolbelt (==0.9.1)
Requires-Dist: requests (==2.22.0)
Requires-Dist: shamir-mnemonic (==0.1.0)
Requires-Dist: six (==1.12.0)
Requires-Dist: snowballstemmer (==1.9.0)
Requires-Dist: sphinxcontrib-websupport (==1.1.2)
Requires-Dist: tqdm (==4.32.2)
Requires-Dist: twine (==1.13.0)
Requires-Dist: typed-ast (==1.3.5)
Requires-Dist: urllib3 (==1.25.3)
Requires-Dist: wcwidth (==0.1.7)
Requires-Dist: webencodings (==0.5.1)
Requires-Dist: zipp (==0.5.2)
